bvzframespec/.___init__.py
bvzframespec/._bvzframespec.py
bvzframespec/__init__.py
bvzframespec/bvzframespec.py
bvzframespec-1.0.2.dist-info/METADATA
bvzframespec-1.0.2.dist-info/WHEEL
bvzframespec-1.0.2.dist-info/licenses/LICENSE
bvzframespec-1.0.2.dist-info/RECORD
