Metadata-Version: 2.1
Name: bvzframespec
Version: 1.0.2
Summary: A library to collapse numberd file lists to a single string.
Project-URL: Homepage, https://github.com/bvz2000/bvzframespec
Project-URL: Bug Tracker, https://github.com/bvz2000/bvzframespec/issues
Author: bvz2000
License-File: LICENSE
Classifier: License :: OSI Approved :: MIT License
Classifier: Operating System :: OS Independent
Classifier: Programming Language :: Python :: 3
Requires-Python: >=3.10
